comp/__init__.py
comp/_version.py
comp/gui_launcher.py
comp/io/__init__.py
comp/io/json_io.py
comp/media/COMP.ico
comp/media/__init__.py
comp/models/__init__.py
comp/models/base.py
comp/models/center.py
comp/models/element.py
comp/parallelization/__init__.py
comp/parallelization/heuristic.py
comp/parallelization/parallel_executor.py
comp/parallelization/core/__init__.py
comp/parallelization/core/device.py
comp/parallelization/core/empiric.py
comp/parallelization/core/operation.py
comp/solvers/__init__.py
comp/solvers/factories.py
comp/solvers/center/__init__.py
comp/solvers/center/linear/__init__.py
comp/solvers/center/linear/first.py
comp/solvers/center/linear/second.py
comp/solvers/center/linear/third.py
comp/solvers/center/linked/__init__.py
comp/solvers/center/linked/first.py
comp/solvers/core/__init__.py
comp/solvers/core/base.py
comp/solvers/core/center.py
comp/solvers/core/element.py
comp/solvers/element/__init__.py
comp/solvers/element/linear/__init__.py
comp/solvers/element/linear/first.py
comp/solvers/element/linear/second.py
comp/ui/__init__.py
comp/ui/config_run_tab.py
comp/ui/data_load_tab.py
comp/ui/main_window.py
comp/ui/results_tab.py
comp/ui/styles.py
comp/ui/worker.py
comp/utils/__init__.py
comp/utils/assertions.py
comp/utils/helpers.py
comp/utils/json_base_serializer.py
lp_comp-2.0.0.dist-info/licenses/LICENSE.md
lp_comp-2.0.0.dist-info/METADATA
lp_comp-2.0.0.dist-info/WHEEL
lp_comp-2.0.0.dist-info/entry_points.txt
lp_comp-2.0.0.dist-info/top_level.txt
lp_comp-2.0.0.dist-info/RECORD
