Metadata-Version: 2.4
Name: lp-comp
Version: 2.0.0
Summary: Mathematical modeling and coordinated planning in two-level organizational-production systems.
Home-page: https://github.com/TheMegistone4Ever/COMP
Author: Mykyta Kyselov (TheMegistone4Ever)
Author-email: zeusmobilenick@gmail.com
License: CC BY-NC 4.0
Classifier: Development Status :: 4 - Beta
Classifier: Intended Audience :: Developers
Classifier: Intended Audience :: Science/Research
Classifier: License :: Other/Proprietary License
Classifier: Operating System :: OS Independent
Classifier: Programming Language :: Python :: 3
Classifier: Programming Language :: Python :: 3.12
Classifier: Topic :: Scientific/Engineering :: Mathematics
Classifier: Topic :: Software Development :: Libraries :: Python Modules
Classifier: Topic :: Utilities
Requires-Python: >=3.12
License-File: LICENSE.md
Requires-Dist: numpy~=2.2.5
Requires-Dist: PyQt5~=5.15.11
Requires-Dist: tabulate~=0.9.0
Requires-Dist: ortools~=9.12.4544
Dynamic: license-file
